onnx2json/__init__.py
onnx2json/__main__.py
onnx2json/onnx2json.py
onnx2json-2.0.4.dist-info/LICENSE
onnx2json-2.0.4.dist-info/METADATA
onnx2json-2.0.4.dist-info/WHEEL
onnx2json-2.0.4.dist-info/entry_points.txt
onnx2json-2.0.4.dist-info/top_level.txt
onnx2json-2.0.4.dist-info/RECORD
