Metadata-Version: 2.1
Name: onnx2json
Version: 2.0.4
Summary: Exports the ONNX file to a JSON file or JSON dict.
Home-page: https://github.com/PINTO0309/onnx2json
Author: Katsuya Hyodo
Author-email: rmsdh122@yahoo.co.jp
License: MIT License
Platform: linux
Platform: unix
Requires-Python: >=3.6
License-File: LICENSE
